lcd_tools/__init__.py
lcd_tools/lcd_utils.py
lcd_tools-0.1.88.dist-info/LICENSE.md
lcd_tools-0.1.88.dist-info/METADATA
lcd_tools-0.1.88.dist-info/WHEEL
lcd_tools-0.1.88.dist-info/RECORD
