Metadata-Version: 2.1
Name: lcd-tools
Version: 0.1.88
Summary: lcd-tools expands upon the RPLCD library to provide short-cut commands for various LCD Display control options. 
Home-page: https://github.com/GabeBen3/lcd-tools
License: MIT
Author: Gabriel Benavidez
Author-email: gbenavidez@ucmerced.edu
Requires-Python: >=3.7,<4.0
Classifier: License :: OSI Approved :: MIT License
Classifier: Programming Language :: Python :: 3
Classifier: Programming Language :: Python :: 3.7
Classifier: Programming Language :: Python :: 3.8
Classifier: Programming Language :: Python :: 3.9
Classifier: Programming Language :: Python :: 3.10
Classifier: Programming Language :: Python :: 3.11
Classifier: Programming Language :: Python :: 3.12
Requires-Dist: rpi-gpio (>=0.7.1,<0.8.0)
Requires-Dist: rplcd (>=1.3.1,<2.0.0)
Project-URL: Repository, https://github.com/GabeBen3/lcd-tools
